drip.py
setup.cfg
setup.py
drip.egg-info/PKG-INFO
drip.egg-info/SOURCES.txt
drip.egg-info/dependency_links.txt
drip.egg-info/requires.txt
drip.egg-info/top_level.txt