Metadata-Version: 1.1
Name: drip
Version: 1.0.8
Summary: A library for exploring multivariate datasets
Home-page: https://github.com/litl/drip
Author: Bob Green
Author-email: bgreen@litl.com
License: MIT
Download-URL: https://github.com/litl/drip/tarball/v1.0.8
Platform: UNKNOWN
Classifier: Development Status :: 5 - Production/Stable
Classifier: Intended Audience :: Developers
Classifier: License :: OSI Approved :: MIT License
Classifier: Operating System :: OS Independent
Classifier: Programming Language :: Python
Classifier: Programming Language :: Python :: 2.7
Classifier: Programming Language :: Python :: 3.4
